<?xml version="1.0" ?>
<World WorldIndex="3">
	<CommonDropPool MinMobLevel="1" MaxMobLevel="7">
		<Item ItemID="16" ItemOption="0" ItemDuration="0" OptionPoolID="1" Rate="0.70875000000000000"/>
		<Item ItemID="31" ItemOption="0" ItemDuration="0" OptionPoolID="1" Rate="0.70875000000000000"/>
		<Item ItemID="46" ItemOption="0" ItemDuration="0" OptionPoolID="1" Rate="0.70875000000000000"/>
		<Item ItemID="61" ItemOption="0" ItemDuration="0" OptionPoolID="1" Rate="0.70875000000000000"/>
		<Item ItemID="76" ItemOption="0" ItemDuration="0" OptionPoolID="1" Rate="0.53125000000000000"/>
		<Item ItemID="91" ItemOption="0" ItemDuration="0" OptionPoolID="1" Rate="0.53125000000000000"/>
		<Item ItemID="106" ItemOption="0" ItemDuration="0" OptionPoolID="1" Rate="0.66875000000000000"/>
		<Item ItemID="121" ItemOption="0" ItemDuration="0" OptionPoolID="1" Rate="0.66875000000000000"/>
		<Item ItemID="136" ItemOption="0" ItemDuration="0" OptionPoolID="1" Rate="0.66875000000000000"/>
		<Item ItemID="151" ItemOption="0" ItemDuration="0" OptionPoolID="1" Rate="0.70875000000000000"/>
		<Item ItemID="166" ItemOption="0" ItemDuration="0" OptionPoolID="1" Rate="0.70875000000000000"/>
		<Item ItemID="181" ItemOption="0" ItemDuration="0" OptionPoolID="1" Rate="0.70875000000000000"/>
		<Item ItemID="196" ItemOption="0" ItemDuration="0" OptionPoolID="1" Rate="0.66875000000000000"/>
		<Item ItemID="211" ItemOption="0" ItemDuration="0" OptionPoolID="1" Rate="0.66875000000000000"/>
		<Item ItemID="226" ItemOption="0" ItemDuration="0" OptionPoolID="1" Rate="0.66875000000000000"/>
		<Item ItemID="241" ItemOption="0" ItemDuration="0" OptionPoolID="1" Rate="0.66875000000000000"/>
		<Item ItemID="256" ItemOption="0" ItemDuration="0" OptionPoolID="1" Rate="0.66875000000000000"/>
		<Item ItemID="271" ItemOption="0" ItemDuration="0" OptionPoolID="1" Rate="0.66875000000000000"/>
		<Item ItemID="285" ItemOption="0" ItemDuration="0" OptionPoolID="0" Rate="0.03125000000000000"/>
		<Item ItemID="293" ItemOption="0" ItemDuration="0" OptionPoolID="0" Rate="0.03125000000000000"/>
		<Item ItemID="301" ItemOption="0" ItemDuration="0" OptionPoolID="0" Rate="0.03125000000000000"/>
		<Item ItemID="309" ItemOption="0" ItemDuration="0" OptionPoolID="0" Rate="0.03125000000000000"/>
		<Item ItemID="312" ItemOption="0" ItemDuration="0" OptionPoolID="0" Rate="0.03125000000000000"/>
		<Item ItemID="350" ItemOption="0" ItemDuration="0" OptionPoolID="0" Rate="0.03125000000000000"/>
		<Item ItemID="354" ItemOption="0" ItemDuration="0" OptionPoolID="0" Rate="0.03125000000000000"/>
		<Item ItemID="358" ItemOption="0" ItemDuration="0" OptionPoolID="0" Rate="0.03125000000000000"/>
		<Item ItemID="33554775" ItemOption="0" ItemDuration="0" OptionPoolID="1" Rate="0.53125000000000000"/>
	</CommonDropPool>
	<CommonDropPool MinMobLevel="8" MaxMobLevel="20">
		<Item ItemID="17" ItemOption="0" ItemDuration="0" OptionPoolID="2" Rate="0.70875000000000000"/>
		<Item ItemID="32" ItemOption="0" ItemDuration="0" OptionPoolID="2" Rate="0.70875000000000000"/>
		<Item ItemID="47" ItemOption="0" ItemDuration="0" OptionPoolID="2" Rate="0.70875000000000000"/>
		<Item ItemID="62" ItemOption="0" ItemDuration="0" OptionPoolID="2" Rate="0.70875000000000000"/>
		<Item ItemID="77" ItemOption="0" ItemDuration="0" OptionPoolID="2" Rate="0.53125000000000000"/>
		<Item ItemID="92" ItemOption="0" ItemDuration="0" OptionPoolID="2" Rate="0.53125000000000000"/>
		<Item ItemID="107" ItemOption="0" ItemDuration="0" OptionPoolID="2" Rate="0.66875000000000000"/>
		<Item ItemID="122" ItemOption="0" ItemDuration="0" OptionPoolID="2" Rate="0.66875000000000000"/>
		<Item ItemID="137" ItemOption="0" ItemDuration="0" OptionPoolID="2" Rate="0.66875000000000000"/>
		<Item ItemID="152" ItemOption="0" ItemDuration="0" OptionPoolID="2" Rate="0.70875000000000000"/>
		<Item ItemID="167" ItemOption="0" ItemDuration="0" OptionPoolID="2" Rate="0.70875000000000000"/>
		<Item ItemID="182" ItemOption="0" ItemDuration="0" OptionPoolID="2" Rate="0.70875000000000000"/>
		<Item ItemID="197" ItemOption="0" ItemDuration="0" OptionPoolID="2" Rate="0.66875000000000000"/>
		<Item ItemID="212" ItemOption="0" ItemDuration="0" OptionPoolID="2" Rate="0.66875000000000000"/>
		<Item ItemID="227" ItemOption="0" ItemDuration="0" OptionPoolID="2" Rate="0.66875000000000000"/>
		<Item ItemID="242" ItemOption="0" ItemDuration="0" OptionPoolID="2" Rate="0.66875000000000000"/>
		<Item ItemID="257" ItemOption="0" ItemDuration="0" OptionPoolID="2" Rate="0.66875000000000000"/>
		<Item ItemID="272" ItemOption="0" ItemDuration="0" OptionPoolID="2" Rate="0.66875000000000000"/>
		<Item ItemID="286" ItemOption="0" ItemDuration="0" OptionPoolID="0" Rate="0.03125000000000000"/>
		<Item ItemID="294" ItemOption="0" ItemDuration="0" OptionPoolID="0" Rate="0.03125000000000000"/>
		<Item ItemID="302" ItemOption="0" ItemDuration="0" OptionPoolID="0" Rate="0.03125000000000000"/>
		<Item ItemID="315" ItemOption="0" ItemDuration="0" OptionPoolID="0" Rate="0.03125000000000000"/>
		<Item ItemID="318" ItemOption="0" ItemDuration="0" OptionPoolID="0" Rate="0.03125000000000000"/>
		<Item ItemID="322" ItemOption="0" ItemDuration="0" OptionPoolID="0" Rate="0.03125000000000000"/>
		<Item ItemID="362" ItemOption="0" ItemDuration="0" OptionPoolID="0" Rate="0.03125000000000000"/>
		<Item ItemID="377" ItemOption="0" ItemDuration="0" OptionPoolID="0" Rate="0.03125000000000000"/>
		<Item ItemID="33554776" ItemOption="0" ItemDuration="0" OptionPoolID="2" Rate="0.53125000000000000"/>
	</CommonDropPool>
	<CommonDropPool MinMobLevel="21" MaxMobLevel="33">
		<Item ItemID="18" ItemOption="0" ItemDuration="0" OptionPoolID="3" Rate="0.70875000000000000"/>
		<Item ItemID="33" ItemOption="0" ItemDuration="0" OptionPoolID="3" Rate="0.70875000000000000"/>
		<Item ItemID="48" ItemOption="0" ItemDuration="0" OptionPoolID="3" Rate="0.70875000000000000"/>
		<Item ItemID="63" ItemOption="0" ItemDuration="0" OptionPoolID="3" Rate="0.70875000000000000"/>
		<Item ItemID="78" ItemOption="0" ItemDuration="0" OptionPoolID="3" Rate="0.53125000000000000"/>
		<Item ItemID="93" ItemOption="0" ItemDuration="0" OptionPoolID="3" Rate="0.53125000000000000"/>
		<Item ItemID="108" ItemOption="0" ItemDuration="0" OptionPoolID="3" Rate="0.66875000000000000"/>
		<Item ItemID="123" ItemOption="0" ItemDuration="0" OptionPoolID="3" Rate="0.66875000000000000"/>
		<Item ItemID="138" ItemOption="0" ItemDuration="0" OptionPoolID="3" Rate="0.66875000000000000"/>
		<Item ItemID="153" ItemOption="0" ItemDuration="0" OptionPoolID="3" Rate="0.70875000000000000"/>
		<Item ItemID="168" ItemOption="0" ItemDuration="0" OptionPoolID="3" Rate="0.70875000000000000"/>
		<Item ItemID="183" ItemOption="0" ItemDuration="0" OptionPoolID="3" Rate="0.70875000000000000"/>
		<Item ItemID="198" ItemOption="0" ItemDuration="0" OptionPoolID="3" Rate="0.66875000000000000"/>
		<Item ItemID="213" ItemOption="0" ItemDuration="0" OptionPoolID="3" Rate="0.66875000000000000"/>
		<Item ItemID="228" ItemOption="0" ItemDuration="0" OptionPoolID="3" Rate="0.66875000000000000"/>
		<Item ItemID="243" ItemOption="0" ItemDuration="0" OptionPoolID="3" Rate="0.66875000000000000"/>
		<Item ItemID="258" ItemOption="0" ItemDuration="0" OptionPoolID="3" Rate="0.66875000000000000"/>
		<Item ItemID="273" ItemOption="0" ItemDuration="0" OptionPoolID="3" Rate="0.66875000000000000"/>
		<Item ItemID="287" ItemOption="0" ItemDuration="0" OptionPoolID="0" Rate="0.03125000000000000"/>
		<Item ItemID="295" ItemOption="0" ItemDuration="0" OptionPoolID="0" Rate="0.03125000000000000"/>
		<Item ItemID="351" ItemOption="0" ItemDuration="0" OptionPoolID="0" Rate="0.03125000000000000"/>
		<Item ItemID="355" ItemOption="0" ItemDuration="0" OptionPoolID="0" Rate="0.03125000000000000"/>
		<Item ItemID="359" ItemOption="0" ItemDuration="0" OptionPoolID="0" Rate="0.03125000000000000"/>
		<Item ItemID="369" ItemOption="0" ItemDuration="0" OptionPoolID="0" Rate="0.03125000000000000"/>
		<Item ItemID="372" ItemOption="0" ItemDuration="0" OptionPoolID="0" Rate="0.03125000000000000"/>
		<Item ItemID="378" ItemOption="0" ItemDuration="0" OptionPoolID="0" Rate="0.03125000000000000"/>
		<Item ItemID="33554777" ItemOption="0" ItemDuration="0" OptionPoolID="3" Rate="0.53125000000000000"/>
	</CommonDropPool>
	<CommonDropPool MinMobLevel="34" MaxMobLevel="46">
		<Item ItemID="19" ItemOption="0" ItemDuration="0" OptionPoolID="3" Rate="0.70875000000000000"/>
		<Item ItemID="34" ItemOption="0" ItemDuration="0" OptionPoolID="3" Rate="0.70875000000000000"/>
		<Item ItemID="49" ItemOption="0" ItemDuration="0" OptionPoolID="3" Rate="0.70875000000000000"/>
		<Item ItemID="64" ItemOption="0" ItemDuration="0" OptionPoolID="3" Rate="0.70875000000000000"/>
		<Item ItemID="79" ItemOption="0" ItemDuration="0" OptionPoolID="3" Rate="0.53125000000000000"/>
		<Item ItemID="94" ItemOption="0" ItemDuration="0" OptionPoolID="3" Rate="0.53125000000000000"/>
		<Item ItemID="109" ItemOption="0" ItemDuration="0" OptionPoolID="3" Rate="0.66875000000000000"/>
		<Item ItemID="124" ItemOption="0" ItemDuration="0" OptionPoolID="3" Rate="0.66875000000000000"/>
		<Item ItemID="139" ItemOption="0" ItemDuration="0" OptionPoolID="3" Rate="0.66875000000000000"/>
		<Item ItemID="154" ItemOption="0" ItemDuration="0" OptionPoolID="3" Rate="0.70875000000000000"/>
		<Item ItemID="169" ItemOption="0" ItemDuration="0" OptionPoolID="3" Rate="0.70875000000000000"/>
		<Item ItemID="184" ItemOption="0" ItemDuration="0" OptionPoolID="3" Rate="0.70875000000000000"/>
		<Item ItemID="199" ItemOption="0" ItemDuration="0" OptionPoolID="3" Rate="0.66875000000000000"/>
		<Item ItemID="214" ItemOption="0" ItemDuration="0" OptionPoolID="3" Rate="0.66875000000000000"/>
		<Item ItemID="229" ItemOption="0" ItemDuration="0" OptionPoolID="3" Rate="0.66875000000000000"/>
		<Item ItemID="244" ItemOption="0" ItemDuration="0" OptionPoolID="3" Rate="0.66875000000000000"/>
		<Item ItemID="259" ItemOption="0" ItemDuration="0" OptionPoolID="3" Rate="0.66875000000000000"/>
		<Item ItemID="274" ItemOption="0" ItemDuration="0" OptionPoolID="3" Rate="0.66875000000000000"/>
		<Item ItemID="288" ItemOption="0" ItemDuration="0" OptionPoolID="0" Rate="0.03125000000000000"/>
		<Item ItemID="296" ItemOption="0" ItemDuration="0" OptionPoolID="0" Rate="0.03125000000000000"/>
		<Item ItemID="303" ItemOption="0" ItemDuration="0" OptionPoolID="0" Rate="0.03125000000000000"/>
		<Item ItemID="319" ItemOption="0" ItemDuration="0" OptionPoolID="0" Rate="0.03125000000000000"/>
		<Item ItemID="323" ItemOption="0" ItemDuration="0" OptionPoolID="0" Rate="0.03125000000000000"/>
		<Item ItemID="363" ItemOption="0" ItemDuration="0" OptionPoolID="0" Rate="0.03125000000000000"/>
		<Item ItemID="366" ItemOption="0" ItemDuration="0" OptionPoolID="0" Rate="0.03125000000000000"/>
		<Item ItemID="379" ItemOption="0" ItemDuration="0" OptionPoolID="0" Rate="0.03125000000000000"/>
		<Item ItemID="33554778" ItemOption="0" ItemDuration="0" OptionPoolID="3" Rate="0.53125000000000000"/>
	</CommonDropPool>
	<CommonDropPool MinMobLevel="47" MaxMobLevel="59">
		<Item ItemID="304" ItemOption="0" ItemDuration="0" OptionPoolID="0" Rate="0.03125000000000000"/>
		<Item ItemID="380" ItemOption="0" ItemDuration="0" OptionPoolID="0" Rate="0.03125000000000000"/>
	</CommonDropPool>
	<CommonDropPool MinMobLevel="47" MaxMobLevel="72">
		<Item ItemID="20" ItemOption="0" ItemDuration="0" OptionPoolID="4" Rate="0.05528250000000000"/>
		<Item ItemID="35" ItemOption="0" ItemDuration="0" OptionPoolID="4" Rate="0.05528250000000000"/>
		<Item ItemID="50" ItemOption="0" ItemDuration="0" OptionPoolID="4" Rate="0.05528250000000000"/>
		<Item ItemID="65" ItemOption="0" ItemDuration="0" OptionPoolID="4" Rate="0.05528250000000000"/>
		<Item ItemID="80" ItemOption="0" ItemDuration="0" OptionPoolID="4" Rate="0.04143750000000000"/>
		<Item ItemID="95" ItemOption="0" ItemDuration="0" OptionPoolID="4" Rate="0.04143750000000000"/>
		<Item ItemID="289" ItemOption="0" ItemDuration="0" OptionPoolID="0" Rate="0.03125000000000000"/>
		<Item ItemID="297" ItemOption="0" ItemDuration="0" OptionPoolID="0" Rate="0.03125000000000000"/>
		<Item ItemID="305" ItemOption="0" ItemDuration="0" OptionPoolID="0" Rate="0.03125000000000000"/>
		<Item ItemID="316" ItemOption="0" ItemDuration="0" OptionPoolID="0" Rate="0.03125000000000000"/>
		<Item ItemID="352" ItemOption="0" ItemDuration="0" OptionPoolID="0" Rate="0.03125000000000000"/>
		<Item ItemID="356" ItemOption="0" ItemDuration="0" OptionPoolID="0" Rate="0.03125000000000000"/>
		<Item ItemID="360" ItemOption="0" ItemDuration="0" OptionPoolID="0" Rate="0.03125000000000000"/>
		<Item ItemID="370" ItemOption="0" ItemDuration="0" OptionPoolID="0" Rate="0.03125000000000000"/>
		<Item ItemID="373" ItemOption="0" ItemDuration="0" OptionPoolID="0" Rate="0.03125000000000000"/>
		<Item ItemID="381" ItemOption="0" ItemDuration="0" OptionPoolID="0" Rate="0.03125000000000000"/>
		<Item ItemID="2738" ItemOption="0" ItemDuration="0" OptionPoolID="4" Rate="0.04703400000000000"/>
		<Item ItemID="2739" ItemOption="0" ItemDuration="0" OptionPoolID="4" Rate="0.04703400000000000"/>
		<Item ItemID="2740" ItemOption="0" ItemDuration="0" OptionPoolID="4" Rate="0.04703400000000000"/>
		<Item ItemID="2741" ItemOption="0" ItemDuration="0" OptionPoolID="4" Rate="0.04703400000000000"/>
		<Item ItemID="2742" ItemOption="0" ItemDuration="0" OptionPoolID="4" Rate="0.04703400000000000"/>
		<Item ItemID="2743" ItemOption="0" ItemDuration="0" OptionPoolID="4" Rate="0.04703400000000000"/>
		<Item ItemID="2744" ItemOption="0" ItemDuration="0" OptionPoolID="4" Rate="0.04703400000000000"/>
		<Item ItemID="2745" ItemOption="0" ItemDuration="0" OptionPoolID="4" Rate="0.04703400000000000"/>
		<Item ItemID="2746" ItemOption="0" ItemDuration="0" OptionPoolID="4" Rate="0.04703400000000000"/>
		<Item ItemID="2747" ItemOption="0" ItemDuration="0" OptionPoolID="4" Rate="0.04703400000000000"/>
		<Item ItemID="2748" ItemOption="0" ItemDuration="0" OptionPoolID="4" Rate="0.04703400000000000"/>
		<Item ItemID="2749" ItemOption="0" ItemDuration="0" OptionPoolID="4" Rate="0.04703400000000000"/>
		<Item ItemID="2750" ItemOption="0" ItemDuration="0" OptionPoolID="4" Rate="0.04703400000000000"/>
		<Item ItemID="2751" ItemOption="0" ItemDuration="0" OptionPoolID="4" Rate="0.04703400000000000"/>
		<Item ItemID="2752" ItemOption="0" ItemDuration="0" OptionPoolID="4" Rate="0.04703400000000000"/>
		<Item ItemID="2753" ItemOption="0" ItemDuration="0" OptionPoolID="4" Rate="0.04703400000000000"/>
		<Item ItemID="2754" ItemOption="0" ItemDuration="0" OptionPoolID="4" Rate="0.04703400000000000"/>
		<Item ItemID="2755" ItemOption="0" ItemDuration="0" OptionPoolID="4" Rate="0.04703400000000000"/>
		<Item ItemID="2756" ItemOption="0" ItemDuration="0" OptionPoolID="4" Rate="0.04703400000000000"/>
		<Item ItemID="2757" ItemOption="0" ItemDuration="0" OptionPoolID="4" Rate="0.04703400000000000"/>
		<Item ItemID="2758" ItemOption="0" ItemDuration="0" OptionPoolID="4" Rate="0.04703400000000000"/>
		<Item ItemID="2759" ItemOption="0" ItemDuration="0" OptionPoolID="4" Rate="0.04703400000000000"/>
		<Item ItemID="2760" ItemOption="0" ItemDuration="0" OptionPoolID="4" Rate="0.04703400000000000"/>
		<Item ItemID="2761" ItemOption="0" ItemDuration="0" OptionPoolID="4" Rate="0.04703400000000000"/>
		<Item ItemID="33554779" ItemOption="0" ItemDuration="0" OptionPoolID="4" Rate="0.04143750000000000"/>
		<Item ItemID="33554788" ItemOption="0" ItemDuration="0" OptionPoolID="4" Rate="0.04703400000000000"/>
		<Item ItemID="33554789" ItemOption="0" ItemDuration="0" OptionPoolID="4" Rate="0.04703400000000000"/>
		<Item ItemID="33554790" ItemOption="0" ItemDuration="0" OptionPoolID="4" Rate="0.04703400000000000"/>
		<Item ItemID="33554791" ItemOption="0" ItemDuration="0" OptionPoolID="4" Rate="0.04703400000000000"/>
		<Item ItemID="33555759" ItemOption="0" ItemDuration="0" OptionPoolID="4" Rate="0.04703400000000000"/>
		<Item ItemID="33555760" ItemOption="0" ItemDuration="0" OptionPoolID="4" Rate="0.04703400000000000"/>
		<Item ItemID="33555761" ItemOption="0" ItemDuration="0" OptionPoolID="4" Rate="0.04703400000000000"/>
		<Item ItemID="33555762" ItemOption="0" ItemDuration="0" OptionPoolID="4" Rate="0.04703400000000000"/>
		<Item ItemID="33557074" ItemOption="0" ItemDuration="0" OptionPoolID="4" Rate="0.04703400000000000"/>
		<Item ItemID="33557075" ItemOption="0" ItemDuration="0" OptionPoolID="4" Rate="0.04703400000000000"/>
		<Item ItemID="33557076" ItemOption="0" ItemDuration="0" OptionPoolID="4" Rate="0.04703400000000000"/>
		<Item ItemID="33557077" ItemOption="0" ItemDuration="0" OptionPoolID="4" Rate="0.04703400000000000"/>
	</CommonDropPool>
	<CommonDropPool MinMobLevel="30" MaxMobLevel="200">
		<Item ItemID="1855" ItemOption="0" ItemDuration="31" OptionPoolID="0" Rate="0.00000000000000000"/>
		<Item ItemID="1998" ItemOption="0" ItemDuration="31" OptionPoolID="0" Rate="0.00000000000000000"/>
		<Item ItemID="2013" ItemOption="0" ItemDuration="31" OptionPoolID="0" Rate="0.00000000000000000"/>
		<Item ItemID="2015" ItemOption="0" ItemDuration="31" OptionPoolID="0" Rate="0.00000000000000000"/>
		<Item ItemID="2017" ItemOption="0" ItemDuration="31" OptionPoolID="0" Rate="0.00000000000000000"/>
		<Item ItemID="33555935" ItemOption="0" ItemDuration="31" OptionPoolID="0" Rate="0.00000000000000000"/>
		<Item ItemID="33555938" ItemOption="0" ItemDuration="31" OptionPoolID="0" Rate="0.00000000000000000"/>
		<Item ItemID="2121" ItemOption="0" ItemDuration="31" OptionPoolID="0" Rate="0.00000000000000000"/>
		<Item ItemID="2123" ItemOption="0" ItemDuration="31" OptionPoolID="0" Rate="0.00000000000000000"/>
		<Item ItemID="2124" ItemOption="0" ItemDuration="31" OptionPoolID="0" Rate="0.00000000000000000"/>
		<Item ItemID="2125" ItemOption="0" ItemDuration="31" OptionPoolID="0" Rate="0.00000000000000000"/>
		<Item ItemID="2126" ItemOption="0" ItemDuration="31" OptionPoolID="0" Rate="0.00000000000000000"/>
		<Item ItemID="2127" ItemOption="0" ItemDuration="31" OptionPoolID="0" Rate="0.00000000000000000"/>
	</CommonDropPool>
	<CommonDropPool MinMobLevel="1" MaxMobLevel="200">
		<Item ItemID="33556695" ItemOption="1" ItemDuration="0" OptionPoolID="0" Rate="1.00000000000000000"/>
	</CommonDropPool>
	<MobDropPool MobSpeciesIndex="1699">
		<Item ItemID="527319" ItemOption="0" ItemDuration="0" OptionPoolID="0" Rate="30.00000000000000000"/>
		<Item ItemID="527325" ItemOption="0" ItemDuration="0" OptionPoolID="0" Rate="30.00000000000000000"/>
	</MobDropPool>
	<MobDropPool MobSpeciesIndex="1702">
		<Item ItemID="527211" ItemOption="268435477" ItemDuration="0" OptionPoolID="0" Rate="18.00000000000000000"/>
		<Item ItemID="527217" ItemOption="268435477" ItemDuration="0" OptionPoolID="0" Rate="18.00000000000000000"/>
		<Item ItemID="527223" ItemOption="268435477" ItemDuration="0" OptionPoolID="0" Rate="18.00000000000000000"/>
		<Item ItemID="527229" ItemOption="268435477" ItemDuration="0" OptionPoolID="0" Rate="18.00000000000000000"/>
		<Item ItemID="527235" ItemOption="268435477" ItemDuration="0" OptionPoolID="0" Rate="7.00000000000000000"/>
		<Item ItemID="527241" ItemOption="268435477" ItemDuration="0" OptionPoolID="0" Rate="8.00000000000000000"/>
		<Item ItemID="34079144" ItemOption="268435477" ItemDuration="0" OptionPoolID="0" Rate="13.00000000000000000"/>
	</MobDropPool>
	<MobDropPool MobSpeciesIndex="1705">
		<Item ItemID="527269" ItemOption="536875794" ItemDuration="0" OptionPoolID="0" Rate="16.66666666666660000"/>
		<Item ItemID="527270" ItemOption="536875794" ItemDuration="0" OptionPoolID="0" Rate="16.66666666666660000"/>
		<Item ItemID="34080234" ItemOption="536877854" ItemDuration="0" OptionPoolID="0" Rate="16.66666666666660000"/>
		<Item ItemID="527287" ItemOption="536877854" ItemDuration="0" OptionPoolID="0" Rate="16.66666666666660000"/>
		<Item ItemID="527288" ItemOption="536877854" ItemDuration="0" OptionPoolID="0" Rate="16.66666666666660000"/>
		<Item ItemID="34080237" ItemOption="536877854" ItemDuration="0" OptionPoolID="0" Rate="16.66666666666660000"/>
	</MobDropPool>
	<MobDropPool MobSpeciesIndex="1708">
		<Item ItemID="527251" ItemOption="536876318" ItemDuration="0" OptionPoolID="0" Rate="16.66666666666660000"/>
		<Item ItemID="527252" ItemOption="536876318" ItemDuration="0" OptionPoolID="0" Rate="16.66666666666660000"/>
		<Item ItemID="34080231" ItemOption="536876318" ItemDuration="0" OptionPoolID="0" Rate="16.66666666666660000"/>
		<Item ItemID="527305" ItemOption="536875540" ItemDuration="0" OptionPoolID="0" Rate="16.66666666666660000"/>
		<Item ItemID="527306" ItemOption="536875540" ItemDuration="0" OptionPoolID="0" Rate="16.66666666666660000"/>
		<Item ItemID="34080240" ItemOption="536875540" ItemDuration="0" OptionPoolID="0" Rate="16.66666666666660000"/>
	</MobDropPool>
	<MobDropPool MobSpeciesIndex="1709">
		<Item ItemID="527320" ItemOption="0" ItemDuration="0" OptionPoolID="0" Rate="30.00000000000000000"/>
		<Item ItemID="527334" ItemOption="0" ItemDuration="0" OptionPoolID="0" Rate="30.00000000000000000"/>
	</MobDropPool>
	<MobDropPool MobSpeciesIndex="1713">
		<Item ItemID="527253" ItemOption="536878609" ItemDuration="0" OptionPoolID="0" Rate="8.33333333333333000"/>
		<Item ItemID="527254" ItemOption="536878609" ItemDuration="0" OptionPoolID="0" Rate="8.33333333333333000"/>
		<Item ItemID="527271" ItemOption="536875282" ItemDuration="0" OptionPoolID="0" Rate="8.33333333333333000"/>
		<Item ItemID="527272" ItemOption="536875282" ItemDuration="0" OptionPoolID="0" Rate="8.33333333333333000"/>
		<Item ItemID="527289" ItemOption="536878609" ItemDuration="0" OptionPoolID="0" Rate="8.33333333333333000"/>
		<Item ItemID="527290" ItemOption="536878609" ItemDuration="0" OptionPoolID="0" Rate="8.33333333333333000"/>
		<Item ItemID="527307" ItemOption="536875540" ItemDuration="0" OptionPoolID="0" Rate="8.33333333333333000"/>
		<Item ItemID="527308" ItemOption="536875540" ItemDuration="0" OptionPoolID="0" Rate="8.33333333333333000"/>
		<Item ItemID="34080232" ItemOption="536875540" ItemDuration="0" OptionPoolID="0" Rate="8.33333333333333000"/>
		<Item ItemID="34080235" ItemOption="536875540" ItemDuration="0" OptionPoolID="0" Rate="8.33333333333333000"/>
		<Item ItemID="34080238" ItemOption="536875540" ItemDuration="0" OptionPoolID="0" Rate="8.33333333333333000"/>
		<Item ItemID="34080241" ItemOption="536875540" ItemDuration="0" OptionPoolID="0" Rate="8.33333333333333000"/>
	</MobDropPool>
	<MobDropPool MobSpeciesIndex="658">
		<Item ItemID="1" ItemOption="0" ItemDuration="0" OptionPoolID="0" Rate="14.00000000000000000"/>
		<Item ItemID="2" ItemOption="0" ItemDuration="0" OptionPoolID="0" Rate="16.00000000000000000"/>
		<Item ItemID="9" ItemOption="0" ItemDuration="0" OptionPoolID="0" Rate="14.00000000000000000"/>
		<Item ItemID="10" ItemOption="0" ItemDuration="0" OptionPoolID="0" Rate="14.00000000000000000"/>
		<Item ItemID="579" ItemOption="1" ItemDuration="0" OptionPoolID="0" Rate="14.00000000000000000"/>
		<Item ItemID="580" ItemOption="1" ItemDuration="0" OptionPoolID="0" Rate="14.00000000000000000"/>
		<Item ItemID="581" ItemOption="1" ItemDuration="0" OptionPoolID="0" Rate="14.00000000000000000"/>
	</MobDropPool>
	<QuestDropPool MobSpeciesIndex="9">
		<Item ItemID="1103" ItemOption="617" ItemDuration="0" OptionPoolID="0" Rate="70.00000000000000000"/>
	</QuestDropPool>
	<QuestDropPool MobSpeciesIndex="353">
		<Item ItemID="1103" ItemOption="618" ItemDuration="0" OptionPoolID="0" Rate="58.00000000000000000"/>
		<Item ItemID="456" ItemOption="3273" ItemDuration="0" OptionPoolID="0" Rate="70.00000000000000000"/>
		<Item ItemID="2869" ItemOption="3274" ItemDuration="0" OptionPoolID="0" Rate="70.00000000000000000"/>
	</QuestDropPool>
	<QuestDropPool MobSpeciesIndex="13">
		<Item ItemID="1103" ItemOption="620" ItemDuration="0" OptionPoolID="0" Rate="78.00000000000000000"/>
	</QuestDropPool>
	<QuestDropPool MobSpeciesIndex="69">
		<Item ItemID="466" ItemOption="3010" ItemDuration="0" OptionPoolID="0" Rate="100.00000000000000000"/>
		<Item ItemID="470" ItemOption="3027" ItemDuration="0" OptionPoolID="0" Rate="100.00000000000000000"/>
		<Item ItemID="469" ItemOption="3042" ItemDuration="0" OptionPoolID="0" Rate="100.00000000000000000"/>
	</QuestDropPool>
	<QuestDropPool MobSpeciesIndex="78">
		<Item ItemID="456" ItemOption="3045" ItemDuration="0" OptionPoolID="0" Rate="100.00000000000000000"/>
	</QuestDropPool>
	<QuestDropPool MobSpeciesIndex="77">
		<Item ItemID="2824" ItemOption="3047" ItemDuration="0" OptionPoolID="0" Rate="100.00000000000000000"/>
	</QuestDropPool>
	<QuestDropPool MobSpeciesIndex="25">
		<Item ItemID="2689" ItemOption="3067" ItemDuration="0" OptionPoolID="0" Rate="100.00000000000000000"/>
	</QuestDropPool>
	<QuestDropPool MobSpeciesIndex="8">
		<Item ItemID="451" ItemOption="3075" ItemDuration="0" OptionPoolID="0" Rate="100.00000000000000000"/>
		<Item ItemID="508" ItemOption="3257" ItemDuration="0" OptionPoolID="0" Rate="40.00000000000000000"/>
	</QuestDropPool>
	<QuestDropPool MobSpeciesIndex="362">
		<Item ItemID="2831" ItemOption="3225" ItemDuration="0" OptionPoolID="0" Rate="80.00000000000000000"/>
	</QuestDropPool>
	<QuestDropPool MobSpeciesIndex="62">
		<Item ItemID="2823" ItemOption="3227" ItemDuration="0" OptionPoolID="0" Rate="80.00000000000000000"/>
	</QuestDropPool>
	<QuestDropPool MobSpeciesIndex="63">
		<Item ItemID="2822" ItemOption="3229" ItemDuration="0" OptionPoolID="0" Rate="80.00000000000000000"/>
	</QuestDropPool>
	<QuestDropPool MobSpeciesIndex="363">
		<Item ItemID="2821" ItemOption="3242" ItemDuration="0" OptionPoolID="0" Rate="70.00000000000000000"/>
	</QuestDropPool>
	<QuestDropPool MobSpeciesIndex="352">
		<Item ItemID="453" ItemOption="3265" ItemDuration="0" OptionPoolID="0" Rate="70.00000000000000000"/>
	</QuestDropPool>
</World>
