<?xml version="1.0" ?>
<MobPattern Index="525">
	<MobTriggerGroup Index="1" Type="1" Parameters="1000">
		<MobActionGroup Index="1" Delay="">
			<MobAction Index="1" Type="10" Parameters="1112:8764:2976:3502" Duration="2000" TargetType="1" TargetParameters="" Loop="1" LoopDelay="3000" Priority="0"/>
		</MobActionGroup>
	</MobTriggerGroup>
	<MobTriggerGroup Index="2" Type="11" Parameters="180000">
		<MobActionGroup Index="2" Delay="">
			<MobAction Index="1" Type="13" Parameters="0" Duration="1000" TargetType="" TargetParameters="" Loop="0" LoopDelay="100000" Priority="5"/>
		</MobActionGroup>
	</MobTriggerGroup>
	<MobPool/>
</MobPattern>
