<?xml version="1.0" ?>
<MobPattern Index="805">
	<MobTriggerGroup Index="1" Type="1" Parameters="3000">
		<MobActionGroup Index="1" Delay="">
			<MobAction Index="1" Type="10" Parameters="1767:60000:3200:3600" Duration="3000" TargetType="1" TargetParameters="" Loop="1" LoopDelay="3000" Priority="0"/>
		</MobActionGroup>
	</MobTriggerGroup>
	<MobTriggerGroup Index="2" Type="1" Parameters="10000">
		<MobActionGroup Index="2" Delay="">
			<MobAction Index="1" Type="10" Parameters="1768:60000:3200:3600" Duration="3000" TargetType="5" TargetParameters="" Loop="1" LoopDelay="10000" Priority="0"/>
		</MobActionGroup>
	</MobTriggerGroup>
	<MobTriggerGroup Index="3" Type="1" Parameters="30000">
		<MobActionGroup Index="3" Delay="">
			<MobAction Index="1" Type="9" Parameters="10" Duration="1000" TargetType="5" TargetParameters="" Loop="1" LoopDelay="30000" Priority="0"/>
		</MobActionGroup>
	</MobTriggerGroup>
	<MobTriggerGroup Index="4" Type="5" Parameters="3:1">
		<MobActionGroup Index="4" Delay="1000">
			<MobAction Index="1" Type="2" Parameters="169:113" Duration="1000" TargetType="5" TargetParameters="" Loop="0" LoopDelay="100000" Priority="0"/>
			<MobAction Index="2" Type="2" Parameters="169:103" Duration="1000" TargetType="5" TargetParameters="" Loop="0" LoopDelay="100000" Priority="0"/>
			<MobAction Index="3" Type="2" Parameters="169:103" Duration="1000" TargetType="5" TargetParameters="" Loop="0" LoopDelay="100000" Priority="0"/>
		</MobActionGroup>
	</MobTriggerGroup>
	<MobTriggerGroup Index="5" Type="11" Parameters="180001">
		<MobActionGroup Index="5" Delay="">
			<MobAction Index="1" Type="13" Parameters="0" Duration="1000" TargetType="" TargetParameters="" Loop="0" LoopDelay="100000" Priority="5"/>
		</MobActionGroup>
	</MobTriggerGroup>
	<MobPool/>
</MobPattern>
